LICENSE.txt
MANIFEST.in
README.md
README.rst
setup.cfg
setup.py
NbUrnClient.egg-info/PKG-INFO
NbUrnClient.egg-info/SOURCES.txt
NbUrnClient.egg-info/dependency_links.txt
NbUrnClient.egg-info/requires.txt
NbUrnClient.egg-info/top_level.txt
nb_urn_client/__init__.py
nb_urn_client/nb_urn_client.py