Metadata-Version: 1.0
Name: NbUrnClient
Version: 0.8.0
Summary: Python Client for the URN PID service at the National Library of Norway
Home-page: https://github.com/runelk/NB_URN_Client_Python
Author: Rune Lain Knudsen
Author-email: rune.knudsen@uib.no
License: LICENSE.txt
Platform: UNKNOWN
